{
    "book_club": [
        {
            "columns": {
                "book_club_id": "The unique identifier for each book club entry.",
                "Year": "The publication year of the book.",
                "Author_or_Editor": "The name of the book's author or editor.",
                "Book_Title": "The title of the book listed in the book club.",
                "Publisher": "The name of the publisher of the book.",
                "Category": "The genre or category of the book.",
                "Result": "The award result associated with the book."
            },
            "table_description": "The table catalogs book club entries with publication details."
        }
    ],
    "movie": [
        {
            "columns": {
                "movie_id": "The unique identifier for each movie entry.",
                "Title": "The name of the movie as presented.",
                "Year": "The year the movie was released.",
                "Director": "The name of the director of the movie.",
                "Budget_million": "The production budget of the movie in millions.",
                "Gross_worldwide": "The total worldwide gross revenue of the movie."
            },
            "table_description": "The table records details about various movies produced."
        }
    ],
    "culture_company": [
        {
            "columns": {
                "Company_name": "The unique name of the culture company.",
                "Type": "The operational type of the culture company.",
                "Incorporated_in": "The location where the company was incorporated.",
                "Group_Equity_Shareholding": "The percentage of equity shareholding in the group.",
                "book_club_id": "The identifier for the associated book club.",
                "movie_id": "The identifier for the associated movie."
            },
            "table_description": "The table tracks culture companies and their affiliations."
        }
    ]
}