{
    "Addresses": [
        {
            "columns": {
                "address_content": "The main line of the address including street details.",
                "other_address_details": "The additional information regarding the address.",
                "country": "The nation where the address is located.",
                "address_id": "The unique identifier for each address entry.",
                "state_province_county": "The specific state, province, or county of the address.",
                "city": "The city where the address is situated.",
                "zip_postcode": "The postal code for the address."
            },
            "table_description": "The table stores addresses linked to customers."
        }
    ],
    "Products": [
        {
            "columns": {
                "product_id": "The unique identifier for each product entry.",
                "product_details": "The description of the product including its name."
            },
            "table_description": "The table stores products available for customer orders."
        }
    ],
    "Customers": [
        {
            "columns": {
                "customer_id": "The unique identifier for each customer.",
                "payment_method": "The method used for payment, such as cash or credit card.",
                "customer_name": "The full name of the customer.",
                "date_became_customer": "The date and time when the customer registered.",
                "other_customer_details": "The additional information related to the customer."
            },
            "table_description": "The table stores customer information for transactions."
        }
    ],
    "Customer_Orders": [
        {
            "columns": {
                "order_id": "The unique identifier for each order made by customers.",
                "customer_id": "The unique identifier for the customer placing the order.",
                "order_status": "The current status of the order, such as Delivered or Cancelled.",
                "order_date": "The date and time when the order was placed.",
                "order_details": "The additional information related to the order."
            },
            "table_description": "The table stores orders placed by customers with their details."
        }
    ],
    "Customer_Addresses": [
        {
            "columns": {
                "customer_id": "The unique identifier for each customer associated with an address.",
                "address_id": "The unique identifier for each address linked to a customer.",
                "date_address_from": "The date when the customer started using the address.",
                "address_type": "The category of the address, such as Billing or Residential.",
                "date_address_to": "The date when the customer stopped using the address."
            },
            "table_description": "The table links customers to their addresses over specified time periods."
        }
    ],
    "Customer_Contact_Channels": [
        {
            "columns": {
                "customer_id": "The unique identifier for each customer associated with a contact channel.",
                "channel_code": "The type of contact channel, such as Mobile or Email.",
                "active_from_date": "The date and time when the contact channel became active.",
                "active_to_date": "The date and time when the contact channel was deactivated.",
                "contact_number": "The phone number or identifier for the contact channel."
            },
            "table_description": "The table stores contact channels linked to customers with their active periods."
        }
    ],
    "Order_Items": [
        {
            "columns": {
                "product_id": "The unique identifier for each product in the order.",
                "order_id": "The unique identifier for the order containing the items.",
                "order_quantity": "The quantity of each product ordered in the transaction."
            },
            "table_description": "The table stores items associated with each customer order."
        }
    ]
}