{
    "Things": [
        {
            "columns": {
                "thing_id": "The unique identifier for each thing.",
                "organization_id": "The identifier linking each thing to its organization.",
                "Type_of_Thing_Code": "The category classification of the thing.",
                "service_type_code": "The code indicating the type of service offered.",
                "service_details": "The specific details regarding the service satisfaction."
            },
            "table_description": "The table records various things and their associated services."
        }
    ],
    "Customers": [
        {
            "columns": {
                "customer_id": "The unique identifier for each customer.",
                "customer_details": "The information detailing each customer's profile."
            },
            "table_description": "The table records customer information for local government services."
        }
    ],
    "Properties": [
        {
            "columns": {
                "property_id": "The unique identifier for each property.",
                "property_type_code": "The code defining the type of property.",
                "property_address": "The address where the property is located.",
                "other_details": "The additional information regarding the property."
            },
            "table_description": "The table holds records of properties in the local government area."
        }
    ],
    "Residents": [
        {
            "columns": {
                "resident_id": "The unique identifier for each resident.",
                "property_id": "The identifier linking the resident to their property.",
                "date_moved_in": "The date when the resident moved into the property.",
                "date_moved_out": "The date when the resident moved out of the property.",
                "other_details": "The additional information regarding the resident."
            },
            "table_description": "The table records residents and their property occupancy details."
        }
    ],
    "Organizations": [
        {
            "columns": {
                "organization_id": "The unique identifier for each organization.",
                "parent_organization_id": "The identifier of the parent organization, if applicable.",
                "organization_details": "The detailed information about each organization."
            },
            "table_description": "The table holds records of organizations within the local government structure."
        }
    ],
    "Customer_Event_Notes": [
        {
            "columns": {
                "Customer_Event_Note_ID": "The unique identifier for each customer event note.",
                "Customer_Event_ID": "The identifier linking to the associated customer event.",
                "service_type_code": "The code indicating the type of service related to the note.",
                "resident_id": "The unique identifier for the resident associated with the note.",
                "property_id": "The unique identifier for the property linked to the note.",
                "date_moved_in": "The date when the resident moved into the property."
            },
            "table_description": "The table records notes related to customer events and their details."
        }
    ],
    "Customer_Events": [
        {
            "columns": {
                "Customer_Event_ID": "The unique identifier for each customer event.",
                "customer_id": "The identifier linking the customer to the event.",
                "date_moved_in": "The date when the resident moved into the property.",
                "property_id": "The identifier linking each event to the associated property.",
                "resident_id": "The unique identifier for the resident involved in the event.",
                "thing_id": "The identifier linking the event to a specific thing."
            },
            "table_description": "The table records customer events related to residents and properties."
        }
    ],
    "Services": [
        {
            "columns": {
                "service_id": "The unique identifier for each service.",
                "organization_id": "The identifier linking the service to its organization.",
                "service_type_code": "The code defining the type of service provided.",
                "service_details": "The satisfaction level regarding the service received."
            },
            "table_description": "The table records various services offered by local government organizations."
        }
    ],
    "Residents_Services": [
        {
            "columns": {
                "resident_id": "The unique identifier for each resident involved in the service.",
                "service_id": "The unique identifier for each service requested by the resident.",
                "date_moved_in": "The date when the resident moved into the property.",
                "property_id": "The unique identifier for the property linked to the resident.",
                "date_requested": "The date when the service request was made.",
                "date_provided": "The date when the requested service was provided.",
                "other_details": "The additional information regarding the service request."
            },
            "table_description": "The table records services requested and provided to residents."
        }
    ],
    "Timed_Status_of_Things": [
        {
            "columns": {
                "thing_id": "The unique identifier for each thing's status record.",
                "Date_and_Date": "The timestamp indicating when the status was recorded.",
                "Status_of_Thing_Code": "The code representing the current status of the thing."
            },
            "table_description": "The table tracks the status of things over specific time intervals."
        }
    ],
    "Timed_Locations_of_Things": [
        {
            "columns": {
                "thing_id": "The unique identifier for each thing's location record.",
                "Date_and_Time": "The timestamp indicating when the location was recorded.",
                "Location_Code": "The code representing the recorded location of the thing."
            },
            "table_description": "The table tracks the historical locations of things at specific times."
        }
    ]
}