{
    "Restaurant": [
        {
            "columns": {
                "ResName": "The name of the restaurant.",
                "ResID": "The unique identifier for each restaurant.",
                "Address": "The physical location of the restaurant.",
                "Rating": "The quality rating of the restaurant on a scale."
            },
            "table_description": "The table provides information about various restaurants."
        }
    ],
    "Visits_Restaurant": [
        {
            "columns": {
                "StuID": "The unique identifier for each student.",
                "ResID": "The unique identifier for each restaurant.",
                "Time": "The timestamp of the restaurant visit.",
                "Spent": "The amount of money spent during the visit."
            },
            "table_description": "The table records student visits to restaurants and their spending."
        }
    ],
    "Student": [
        {
            "columns": {
                "StuID": "The unique identifier for each student.",
                "LName": "The last name of the student.",
                "Fname": "The first name of the student.",
                "Age": "The age of the student in years.",
                "Sex": "The gender of the student, represented by a single character.",
                "Major": "The unique identifier for the student's major field of study.",
                "Advisor": "The unique identifier of the student's academic advisor.",
                "city_code": "The code representing the city where the student resides."
            },
            "table_description": "The table provides information about students and their details."
        }
    ],
    "Type_Of_Restaurant": [
        {
            "columns": {
                "ResID": "The unique identifier for each restaurant.",
                "ResTypeID": "The unique identifier for the type of restaurant."
            },
            "table_description": "The table links restaurants to their respective types."
        }
    ],
    "Restaurant_Type": [
        {
            "columns": {
                "ResTypeID": "The unique identifier for each type of restaurant.",
                "ResTypeName": "The name of the restaurant type.",
                "ResTypeDescription": "The description providing details about the restaurant type."
            },
            "table_description": "The table categorizes types of restaurants with descriptions."
        }
    ]
}