{
    "captain": [
        {
            "columns": {
                "Captain_ID": "A unique identifier for each captain in the database.",
                "Name": "The full name of the captain.",
                "Ship_ID": "A reference to the specific ship that the captain is assigned to.",
                "age": "The age of the captain.",
                "Class": "The classification or type of the ship commanded by the captain.",
                "Rank": "The rank or title held by the captain in naval hierarchy."
            },
            "table_description": "The 'captain' table stores information about various ship captains, including their identities, ranks, ages, and the ships they command, facilitating the management and organization of ship personnel."
        }
    ],
    "Ship": [
        {
            "columns": {
                "Ship_ID": "A unique identifier for each ship in the table.",
                "Name": "The name of the ship, often used for identification and recognition.",
                "Type": "The classification of the ship based on its design and operational purpose.",
                "Built_Year": "The year in which the ship was constructed.",
                "Class": "The classification or standard to which the ship adheres, often related to safety and performance.",
                "Flag": "The country under whose laws the ship is registered."
            },
            "table_description": "The Ship table contains information about various ships, including their identifiers, names, types, construction years, classifications, and registration flags."
        }
    ]
}