{
    "mission": [
        {
            "columns": {
                "Mission_ID": "The unique identifier for each mission.",
                "Ship_ID": "The identifier of the associated ship.",
                "Code": "The mission code used for reference.",
                "Launched_Year": "The year in which the mission was launched.",
                "Location": "The geographical location of the mission.",
                "Speed_knots": "The speed of the ship during the mission in knots.",
                "Fate": "The final status or outcome of the mission."
            },
            "table_description": "The mission table records details about various ship missions."
        }
    ],
    "ship": [
        {
            "columns": {
                "Ship_ID": "The unique identifier for each ship.",
                "Name": "The name of the ship.",
                "Type": "The classification type of the ship.",
                "Nationality": "The country of registration for the ship.",
                "Tonnage": "The weight capacity of the ship in tons."
            },
            "table_description": "The ship table stores details about various ships."
        }
    ]
}