{
    "submission": [
        {
            "columns": {
                "Submission_ID": "The unique identifier for each submission.",
                "Scores": "The numeric score awarded to the submission.",
                "Author": "The name of the person who authored the submission.",
                "College": "The educational institution associated with the author."
            },
            "table_description": "The table tracks submissions and their evaluation details."
        }
    ],
    "Acceptance": [
        {
            "columns": {
                "Submission_ID": "The unique identifier for each submission in the acceptance process.",
                "Workshop_ID": "The unique identifier for each workshop associated with submissions.",
                "Result": "The outcome of the submission, either accepted or rejected."
            },
            "table_description": "The table tracks the acceptance results of submissions to workshops."
        }
    ],
    "workshop": [
        {
            "columns": {
                "Workshop_ID": "The unique identifier for each workshop.",
                "Date": "The date on which the workshop is scheduled.",
                "Venue": "The location where the workshop will take place.",
                "Name": "The title or name of the workshop."
            },
            "table_description": "The table captures details about various workshops."
        }
    ]
}